Workbook

Sheet Leia-me
A1: BASTIÃO SEGURADORA S.A. — Conjunto de dados fictícios para treinamento (seguro garantia)
A3: ATENÇÃO: TODOS OS DADOS SÃO FICTÍCIOS, criados apenas para treinamento. Seguradora, tomadores, apólices, sinistros e números não existem e não representam nenhuma organização real.
A7: A empresa (resumo do caso)
A8: Bastião é uma seguradora brasileira de médio porte especializada em SEGURO GARANTIA, com prêmios emitidos de ~R$ 1,8 bi/ano.
A9: Ramos: Garantia de Execução de Contrato (carro-chefe), Garantia Judicial, Fiança Locatícia e Riscos de Engenharia.
A10: Subscrição (underwriting) é o coração do negócio: avaliar o tomador (risco de crédito) e o contrato/edital garantido.
A11: Situação: a carteira cresce, mas a sinistralidade vem subindo e há forte concentração em Construção Civil e na região Sudeste.
A12: Decisão em aberto no caso: aprovar (ou não) uma grande garantia de execução para a Construtora Pilar, que já é o maior risco da casa.
A14: As abas / arquivos deste pacote
A15: Resumo da Carteira | B15: KPIs trimestrais: prêmio, sinistralidade, índice combinado, resultado de subscrição. Para visão de board.
A16: Apólices | B16: Carteira de apólices: tomador, ramo, setor, importância segurada (IS), prêmio, taxa, vigência, região, status.
A17: Tomadores | B17: Indicadores de crédito dos principais tomadores: alavancagem, liquidez, rating, limite e exposição. Para análise de risco/concentração.
A18: Sinistros | B18: Avisos de sinistro: apólice, tomador, valor reservado, status, causa. Para resumo ao comitê de sinistros.
A19: (arquivo) Edital e Tomador | B19: Documento LONGO: edital + contrato + financeiro da Construtora Pilar. Para o exercício de subscrição.
A20: (arquivo) Condições Gerais | B20: Condições gerais do seguro garantia (juridiquês). Para traduzir e extrair exclusões/obrigações.

Sheet Resumo da Carteira
A1: Bastião Seguradora — Indicadores Trimestrais da Carteira
A2: Valores em R$ milhões, exceto onde indicado. DADOS FICTÍCIOS.
A4: Indicador | B4: 1T24 | C4: 2T24 | D4: 3T24 | E4: 4T24 | F4: 1T25 | G4: 2T25 | H4: 3T25 | I4: 4T25
A5: Prêmio Emitido | B5: 410 | C5: 420 | D5: 435 | E5: 455 | F5: 430 | G5: 445 | H5: 460 | I5: 478
A6: Prêmio Ganho | B6: 395 | C6: 405 | D6: 420 | E6: 440 | F6: 418 | G6: 432 | H6: 447 | I6: 463
A7: Sinistros Incorridos | B7: 87 | C7: 97 | D7: 113 | E7: 136 | F7: 138 | G7: 156 | H7: 174 | I7: 195
A8: Sinistralidade % | B8: =B7/B6 -> 0.22025316 | C8: =C7/C6 -> 0.23950617 | D8: =D7/D6 -> 0.26904762 | E8: =E7/E6 -> 0.30909091 | F8: =F7/F6 -> 0.33014354 | G8: =G7/G6 -> 0.36111111 | H8: =H7/H6 -> 0.38926174 | I8: =I7/I6 -> 0.42116631
A9: Despesas Operacionais | B9: 142 | C9: 146 | D9: 149 | E9: 158 | F9: 155 | G9: 158 | H9: 161 | I9: 169
A10: Índice de Despesas % | B10: =B9/B6 -> 0.35949367 | C10: =C9/C6 -> 0.36049383 | D10: =D9/D6 -> 0.3547619 | E10: =E9/E6 -> 0.35909091 | F10: =F9/F6 -> 0.3708134 | G10: =G9/G6 -> 0.36574074 | H10: =H9/H6 -> 0.36017897 | I10: =I9/I6 -> 0.3650108
A11: Índice Combinado % | B11: =B8+B10 -> 0.57974684 | C11: =C8+C10 -> 0.6 | D11: =D8+D10 -> 0.62380952 | E11: =E8+E10 -> 0.66818182 | F11: =F8+F10 -> 0.70095694 | G11: =G8+G10 -> 0.72685185 | H11: =H8+H10 -> 0.74944072 | I11: =I8+I10 -> 0.78617711
A12: Resultado de Subscrição | B12: =B6-B7-B9 -> 166 | C12: =C6-C7-C9 -> 162 | D12: =D6-D7-D9 -> 158 | E12: =E6-E7-E9 -> 146 | F12: =F6-F7-F9 -> 125 | G12: =G6-G7-G9 -> 118 | H12: =H6-H7-H9 -> 112 | I12: =I6-I7-I9 -> 99
A14: Leitura: a Sinistralidade sobe de ~22% para ~42% em 8 trimestres; o Índice Combinado vai de ~58% para ~79%. Ainda há lucro de subscrição, mas a tendência e a concentração são o tema de board.

Sheet Apólices
A1: Apólice | B1: Tomador | C1: Ramo | D1: Setor do Tomador | E1: Região | F1: IS (R$ mm) | G1: Taxa % | H1: Prêmio (R$ mil) | I1: Início Vigência | J1: Fim Vigência | K1: Status
A2: AP-1001 | B2: Construtora Pilar Engenharia | C2: Garantia de Execução de Contrato | D2: Construção Civil | E2: Sudeste | F2: 36.5 | G2: 0.0228 | H2: =F2*1000*G2 -> 832.2 | I2: 2024-02-15 | J2: 2026-02-15 | K2: Sinistro
A3: AP-1002 | B3: Construtora Pilar Engenharia | C3: Garantia de Execução de Contrato | D3: Construção Civil | E3: Sudeste | F3: 51 | G3: 0.0225 | H3: =F3*1000*G3 -> 1147.5 | I3: 2024-02-15 | J3: 2026-05-15 | K3: Vigente
A4: AP-1003 | B4: Construtora Pilar Engenharia | C4: Garantia de Execução de Contrato | D4: Construção Civil | E4: Sudeste | F4: 28.1 | G4: 0.0242 | H4: =F4*1000*G4 -> 680.02 | I4: 2024-02-15 | J4: 2026-05-15 | K4: Vigente
A5: AP-1004 | B5: Construtora Pilar Engenharia | C5: Garantia de Execução de Contrato | D5: Construção Civil | E5: Sudeste | F5: 29.7 | G5: 0.0241 | H5: =F5*1000*G5 -> 715.77 | I5: 2024-02-15 | J5: 2026-05-15 | K5: Vigente
A6: AP-1005 | B6: Infra Rodovias do Sul | C6: Garantia de Execução de Contrato | D6: Infraestrutura | E6: Sul | F6: 50.5 | G6: 0.0145 | H6: =F6*1000*G6 -> 732.25 | I6: 2024-02-15 | J6: 2026-11-15 | K6: Vigente
A7: AP-1006 | B7: Infra Rodovias do Sul | C7: Garantia de Execução de Contrato | D7: Infraestrutura | E7: Sul | F7: 31.6 | G7: 0.0135 | H7: =F7*1000*G7 -> 426.6 | I7: 2024-05-15 | J7: 2026-08-15 | K7: Vigente
A8: AP-1007 | B8: Infra Rodovias do Sul | C8: Garantia de Execução de Contrato | D8: Infraestrutura | E8: Sul | F8: 43.6 | G8: 0.0144 | H8: =F8*1000*G8 -> 627.84 | I8: 2024-08-15 | J8: 2026-05-15 | K8: Vigente
A9: AP-1008 | B9: EnerGen Energia | C9: Garantia de Execução de Contrato | D9: Energia | E9: Sudeste | F9: 44.5 | G9: 0.0114 | H9: =F9*1000*G9 -> 507.3 | I9: 2024-05-15 | J9: 2026-08-15 | K9: Vigente
A10: AP-1009 | B10: EnerGen Energia | C10: Garantia de Execução de Contrato | D10: Energia | E10: Sudeste | F10: 44.2 | G10: 0.0117 | H10: =F10*1000*G10 -> 517.14 | I10: 2024-02-15 | J10: 2026-05-15 | K10: Vigente
A11: AP-1010 | B11: EnerGen Energia | C11: Garantia de Execução de Contrato | D11: Energia | E11: Sudeste | F11: 61.5 | G11: 0.0113 | H11: =F11*1000*G11 -> 694.95 | I11: 2024-08-15 | J11: 2026-11-15 | K11: Vigente
A12: AP-1011 | B12: Saneamento Águas Claras | C12: Garantia de Execução de Contrato | D12: Saneamento | E12: Nordeste | F12: 44.1 | G12: 0.0182 | H12: =F12*1000*G12 -> 802.62 | I12: 2024-08-15 | J12: 2026-05-15 | K12: Vigente
A13: AP-1012 | B13: Saneamento Águas Claras | C13: Garantia de Execução de Contrato | D13: Saneamento | E13: Nordeste | F13: 50.2 | G13: 0.0191 | H13: =F13*1000*G13 -> 958.82 | I13: 2024-05-15 | J13: 2026-02-15 | K13: Vigente
... A34: AP-1033 | B34: Carteira Fiança Locatícia (pulverizada) | C34: Fiança Locatícia | D34: Imobiliário | E34: Nordeste | F34: 0.13 | G34: 0.048 | H34: =F34*1000*G34 -> 6.24 | I34: 2025-03-01 | J34: 2026-03-01 | K34: Vigente

Sheet Tomadores
A1: Principais Tomadores — Indicadores de Crédito e Exposição
A2: Exposição = soma da IS das apólices do tomador (via fórmula). DADOS FICTÍCIOS.
A4: Tomador | B4: Setor | C4: Receita (R$ mm) | D4: Dívida/EBITDA | E4: Liquidez Corrente | F4: Rating Interno | G4: Limite Aprovado (R$ mm) | H4: Exposição Atual (R$ mm) | I4: % do Limite Usado
A5: Construtora Pilar Engenharia | B5: Construção Civil | C5: 1850 | D5: 4.8 | E5: 0.9 | F5: BB- | G5: 180 | H5: =SUMIF(Apólices!$B$2:$B$34,A5,Apólices!$F$2:$F$34) -> 145.3 | I5: =H5/G5 -> 0.80722222
A6: Infra Rodovias do Sul | B6: Infraestrutura | C6: 2200 | D6: 3.1 | E6: 1.2 | F6: BBB | G6: 150 | H6: =SUMIF(Apólices!$B$2:$B$34,A6,Apólices!$F$2:$F$34) -> 125.7 | I6: =H6/G6 -> 0.838
A7: EnerGen Energia | B7: Energia | C7: 3400 | D7: 2.4 | E7: 1.4 | F7: A- | G7: 200 | H7: =SUMIF(Apólices!$B$2:$B$34,A7,Apólices!$F$2:$F$34) -> 150.2 | I7: =H7/G7 -> 0.751
A8: Saneamento Águas Claras | B8: Saneamento | C8: 1200 | D8: 3.6 | E8: 1.1 | F8: BB+ | G8: 90 | H8: =SUMIF(Apólices!$B$2:$B$34,A8,Apólices!$F$2:$F$34) -> 94.3 | I8: =H8/G8 -> 1.0477778
A9: MetalTech Indústria | B9: Indústria | C9: 800 | D9: 2 | E9: 1.6 | F9: A | G9: 60 | H9: =SUMIF(Apólices!$B$2:$B$34,A9,Apólices!$F$2:$F$34) -> 52.8 | I9: =H9/G9 -> 0.88
A10: Rede Varejo Bom Preço | B10: Varejo | C10: 1500 | D10: 5.2 | E10: 0.8 | F10: B+ | G10: 70 | H10: =SUMIF(Apólices!$B$2:$B$34,A10,Apólices!$F$2:$F$34) -> 46.7 | I10: =H10/G10 -> 0.66714286
A11: Construtora Horizonte | B11: Construção Civil | C11: 950 | D11: 3.9 | E11: 1 | F11: BB | G11: 80 | H11: =SUMIF(Apólices!$B$2:$B$34,A11,Apólices!$F$2:$F$34) -> 87.9 | I11: =H11/G11 -> 1.09875
A12: Logística Trans Brasil | B12: Logística | C12: 620 | D12: 2.7 | E12: 1.3 | F12: BBB- | G12: 45 | H12: =SUMIF(Apólices!$B$2:$B$34,A12,Apólices!$F$2:$F$34) -> 28.8 | I12: =H12/G12 -> 0.64
A13: Porto & Terminais S.A. | B13: Infraestrutura | C13: 2800 | D13: 2.2 | E13: 1.5 | F13: A- | G13: 160 | H13: =SUMIF(Apólices!$B$2:$B$34,A13,Apólices!$F$2:$F$34) -> 182.2 | I13: =H13/G13 -> 1.13875
A14: AgroForte Cooperativa | B14: Agro | C14: 1100 | D14: 2.9 | E14: 1.4 | F14: BBB | G14: 75 | H14: =SUMIF(Apólices!$B$2:$B$34,A14,Apólices!$F$2:$F$34) -> 56.1 | I14: =H14/G14 -> 0.748
A15: TecBuild Empreendimentos | B15: Construção Civil | C15: 540 | D15: 4.4 | E15: 0.95 | F15: BB- | G15: 50 | H15: =SUMIF(Apólices!$B$2:$B$34,A15,Apólices!$F$2:$F$34) -> 46 | I15: =H15/G15 -> 0.92
A16: Sigma Telecom | B16: Telecom | C16: 1900 | D16: 3.3 | E16: 1.2 | F16: BBB | G16: 110 | H16: =SUMIF(Apólices!$B$2:$B$34,A16,Apólices!$F$2:$F$34) -> 106.7 | I16: =H16/G16 -> 0.97
A18: Atenção: a Construtora Pilar combina alavancagem alta (4,8x), liquidez baixa (0,9) e a maior exposição da casa — próxima ou acima do limite. É o foco do exercício de subscrição.

Sheet Sinistros
A1: Sinistro | B1: Apólice | C1: Tomador | D1: Ramo | E1: Data Aviso | F1: Valor Reservado (R$ mm) | G1: Status | H1: Causa Provável
A2: SN-2502 | B2: AP-1001 | C2: Construtora Pilar Engenharia | D2: Garantia de Execução de Contrato | E2: 2025-08-12 | F2: 38 | G2: Em análise | H2: Atraso e risco de inadimplemento em obra de infraestrutura
A3: SN-2503 | B3: AP-1031 | C3: Rede Varejo Bom Preço | D3: Garantia Judicial | E3: 2025-07-03 | F3: 6.5 | G3: Indenizado | H3: Decisão judicial desfavorável ao tomador
A4: SN-2504 | B4: AP-1014 | C4: Saneamento Águas Claras | D4: Garantia de Execução de Contrato | E4: 2025-06-20 | F4: 4.2 | G4: Em regresso | H4: Execução parcial; recuperação em curso
A5: SN-2505 | B5: AP-1007 | C5: EnerGen Energia | D5: Garantia de Execução de Contrato | E5: 2025-05-09 | F5: 2.1 | G5: Negado | H5: Aviso fora das condições de cobertura
A6: SN-2506 | B6: AP-1025 | C6: Construtora Horizonte | D6: Garantia de Execução de Contrato | E6: 2025-09-01 | F6: 9.7 | G6: Em análise | H6: Abandono parcial de obra alegado pelo segurado
A7: SN-2507 | B7: AP-1003 | C7: Construtora Pilar Engenharia | D7: Garantia de Execução de Contrato | E7: 2025-09-22 | F7: 15.3 | G7: Em análise | H7: Pedido de prorrogação negado; risco de inadimplemento
